{
    "hero": {
        "badge": "Partner With Us",
        "title": "DYKESWHOTECH",
        "heading": "EMPOWER DIVERSITY CONNECT WITH TALENTS DRIVE IMPACT",
        "description": [
            "DykesWhoTech is a premier professional ecosystem of over 400 LGBTQ+ women in tech. We bridge the gap between top-tier talent and the industry's leading organizations. With dozens of successful high-impact projects, we are more than a community; we are a grassroots movement building real-world tools and fostering the next generation of tech leadership."
        ],
        "cta": "Our partnership tiers"
    },
    "whyJoin": {
        "title": "WHY JOIN OUR MISSION?",
        "intro": "Partnering with us translates into tangible growth for your organisation:",
        "items": [
            {
                "title": "Access Elite Talent",
                "text": "Reach a highly skilled, niche audience of developers, product managers, and designers that are often missed by traditional recruiting."
            },
            {
                "title": "Boost Brand Authority",
                "text": "Position your organization at the heart of the LGBTQ+ tech space through our flagship events."
            },
            {
                "title": "Lead with DEI",
                "text": "Move beyond slogans. Act on your Diversity, Equity, and inclusion goals with a partner that delivers real representation and results."
            }
        ]
    },
    "engagementOpportunities": {
        "badge": "Engagement Opportunities",
        "title": "CHOOSE THE LEVEL OF ENGAGEMENT THAT BEST FITS YOUR ORGANIZATIONAL GOALS:",
        "subtitle": "What in it for you? - In every partnership tier:",
        "includedItems": [
            {
                "title": "Recruitment Boost",
                "text": "Strategic placement of your open roles across our official website and community platforms."
            },
            {
                "title": "Direct Talent Access",
                "text": "Unfiltered connection to our specialized professional talent pool."
            },
            {
                "title": "Brand Recognition",
                "text": "Featured logo on our partner wall and in our monthly professional newsletter."
            }
        ],
        "tiers": [
            {
                "price": "$2,500",
                "name": "Professional Knowledge Exchange",
                "value": "We provide the expertise; you gain the engagement.",
                "features": [
                    {
                        "title": "Expert-Led Workshop",
                        "text": "We bring top industry leaders to host a technical or product-focused session for your team or our community."
                    },
                    {
                        "title": "Skill Sharing",
                        "text": "Position your company as a place of professional growth and technical excellence."
                    }
                ],
                "cta": "Choose tier"
            },
            {
                "price": "$5,000",
                "name": "LGBTQ+ Leadership Talk",
                "value": "Cultural transformation led by community experts.",
                "features": [
                    {
                        "title": "Educational Keynote",
                        "text": "A high-impact session for your organization on LGBTQ+ inclusion and building diverse tech teams."
                    },
                    {
                        "title": "DEI Roadmap",
                        "text": "Gain practical insights on fostering a truly inclusive environment within your company."
                    }
                ],
                "cta": "Choose tier"
            },
            {
                "price": "$7,500",
                "name": "The Full Experience \"DykesWhoTech\"",
                "value": "Turn your office into a community hub.",
                "features": [
                    {
                        "title": "Signature Event",
                        "text": "A high-energy corporate event produced by us, featuring a professional DJ from our community."
                    },
                    {
                        "title": "Atmosphere & Branding",
                        "text": "Bring the unmistakable DykesWhoTech vibe to your company, creating lasting impressions with top talent."
                    }
                ],
                "cta": "Choose tier"
            }
        ]
    },
    "customImpact": {
        "title": "Custom Impact: Let's Build the Future Together",
        "subtitle": "Looking for a tailored approach?",
        "text": [
            "The options above are our most popular engagement routes, but we believe the best partnerships are bespoke. Whether you need high-volume recruitment, long-term brand positioning, or a unique community initiative, we will tailor a package to fit your specific vision and budget."
        ],
        "cta": "Custom tier"
    }
}
